Compiled from "HeapOOMTest.java"
public class com.china.jvm.HeapOOMTest {
  public com.china.jvm.HeapOOMTest();
    Code:
       0: aload_0
       1: invokespecial #1                  // Method java/lang/Object."<init>":()V
       4: return

  public static void main(java.lang.String[]);
    Code:
       0: new           #2                  // class com/china/jvm/Demo
       3: dup
       4: invokespecial #3                  // Method com/china/jvm/Demo."<init>":()V
       7: astore_1
       8: aload_1
       9: invokevirtual #4                  // Method com/china/jvm/Demo.createObject:()V
      12: return
}
